jscatter/__init__.py
jscatter/_cli.py
jscatter/annotations.py
jscatter/annotations_traits.py
jscatter/bundle.js
jscatter/color_maps.py
jscatter/compose.py
jscatter/composite_annotations.py
jscatter/dependencies.py
jscatter/encodings.py
jscatter/jscatter.py
jscatter/type_guards.py
jscatter/types.py
jscatter/utils.py
jscatter/widget.py
jscatter/font/.gitignore
jscatter/font/README.md
jscatter/font/__init__.py
jscatter/font/arial-bold-italic.json
jscatter/font/arial-bold.json
jscatter/font/arial-italic.json
jscatter/font/arial.json
jscatter/font/font.py
jscatter/font/font_family.py
jscatter/label_placement/__init__.py
jscatter/label_placement/aggregate.py
jscatter/label_placement/center_of_mass.py
jscatter/label_placement/constants.py
jscatter/label_placement/highest_density_point.py
jscatter/label_placement/k.py
jscatter/label_placement/label_placement.py
jscatter/label_placement/largest_cluster.py
jscatter/label_placement/optimize_line_breaks.py
jscatter/label_placement/persistence.py
jscatter/label_placement/resolve_zoom_in_collisions.py
jscatter/label_placement/text.py
jscatter/label_placement/tile.py
jscatter/label_placement/types.py
jscatter/label_placement/utils.py
jscatter/label_placement/validate.py
jscatter/label_placement/zoom_solver.py
jscatter/pycolormap_2d/__init__.py
jscatter/pycolormap_2d/colormap_2d.py
jscatter/pycolormap_2d/data/bremm.npy
jscatter/pycolormap_2d/data/cubediagonal.npy
jscatter/pycolormap_2d/data/schumann.npy
jscatter/pycolormap_2d/data/steiger.npy
jscatter/pycolormap_2d/data/teulingfig2.npy
jscatter/pycolormap_2d/data/ziegler.npy
jscatter/serializers/__init__.py
jscatter/serializers/dataframe.py
jscatter/serializers/ndarray.py
jscatter/traittypes/LICENSE
jscatter/traittypes/README.md
jscatter/traittypes/__init__.py
jscatter/traittypes/array.py
jscatter/traittypes/dataframe.py
jscatter/traittypes/empty.py
jscatter/traittypes/scitype.py
jscatter/widgets/__init__.py
jscatter/widgets/button.py
jscatter/widgets/button_choice.py
jupyter_scatter_scsketch-0.22.0.dist-info/METADATA
jupyter_scatter_scsketch-0.22.0.dist-info/WHEEL
jupyter_scatter_scsketch-0.22.0.dist-info/entry_points.txt
jupyter_scatter_scsketch-0.22.0.dist-info/licenses/LICENSE
jupyter_scatter_scsketch-0.22.0.dist-info/RECORD
