Metadata-Version: 2.4
Name: jupyter-scatter-scsketch
Version: 0.22.0
Summary: An interactive scatter plot widget for Jupyter Notebook, Lab, and Google Colab that can handle millions of points and supports view linking (and adds support for directional search)
Project-URL: homepage, https://jupyter-scatter.dev
Project-URL: documentation, https://jupyter-scatter.dev/api
Project-URL: repository, https://github.com/flekschas/jupyter-scatter
Project-URL: changelog, https://github.com/flekschas/jupyter-scatter/blob/main/CHANGELOG.md
Author-email: Fritz Lekschas <code@lekschas.de>, Andres Colubri <andres.colubri@umassmed.edu>, Askar Temirbek <askar.temirbek@umassmed.edu>
License: Apache-2.0
License-File: LICENSE
Keywords: ipython,ipywidgets,jupyter,jupyterlab,jupyterlab-extension,scatter,scatter plot,widgets
Classifier: Development Status :: 4 - Beta
Classifier: Intended Audience :: Developers
Classifier: Intended Audience :: Science/Research
Classifier: Programming Language :: Python :: 3.9
Classifier: Programming Language :: Python :: 3.10
Classifier: Programming Language :: Python :: 3.11
Classifier: Programming Language :: Python :: 3.12
Classifier: Topic :: Multimedia :: Graphics
Requires-Python: >=3.9
Requires-Dist: anywidget>=0.9.0
Requires-Dist: geoindex-rs
Requires-Dist: ipython
Requires-Dist: ipywidgets<9,>=7.6
Requires-Dist: matplotlib>=3.9
Requires-Dist: numpy
Requires-Dist: pandas
Requires-Dist: pooch>=1.3.0
Requires-Dist: pyarrow
Requires-Dist: scipy
Requires-Dist: typing-extensions
Provides-Extra: all
Requires-Dist: hdbscan; extra == 'all'
Requires-Dist: seaborn; extra == 'all'
Requires-Dist: tqdm; extra == 'all'
Provides-Extra: annotation-extras
Requires-Dist: seaborn; extra == 'annotation-extras'
Provides-Extra: label-extras
Requires-Dist: hdbscan; extra == 'label-extras'
Requires-Dist: tqdm; extra == 'label-extras'
